{
  "commonConfig": {
  },
  "tabConfig": {
    "allMedicationTabConfig": {
      "inputOptionsConfig": {
        "allowOnlyCodedDrugs" : true,
        "defaultDurationUnit": "Jour(s)",
        "hideOrderSet" : true,
        "defaultInstructions": "As directed",
        "hiddenFields": ["sos","dosingTypeToggle"],
        "frequencyDefaultDurationUnitsMap": [
          {
            "minFrequency": "1/7",
            "maxFrequency": 5,
            "defaultDurationUnit": "Jour(s)"
          },
          {
            "minFrequency": "1/30",
            "maxFrequency": "1/7",
            "defaultDurationUnit": "Semaine(s)"
          },
          {
            "minFrequency": null,
            "maxFrequency": "1/30",
            "defaultDurationUnit": "Mois(s)"
          }
        ],
        "drugFormDefaults": {


        "ml": {
            "doseUnits": "ml",
            "route": "Orale"
        },
        "Capsule":{
          "doseUnits": "Capsule",
          "route": "Orale"
        },
        "Comprimé" : {
            "doseUnits": "Comprimé",
            "route": "Orale"
        },
        "gélule":{
          "doseUnits": "gélule",
          "route": "Orale"
        },
        "boite" : {
        	"doseUnits": "boite",
        	"route": "application locale"
	      },
        "g" : {
          	"doseUnits": "g",
          	"route": "Orale"
	        },
        "bouffée" : {
          "doseUnits": "bouffée",
          "route": "Puff"
        },
        "mg" : {
          "doseUnits": "mg",
	        "route": "injectable"
        },
        "Dose" : {
          "doseUnits": "Dose",
	        "route": "injectable"
        },
        "application" : {
            "doseUnits": "application",
            "route": "application locale"
        },
        "goutte": {
            "doseUnits": "goutte",
            "route": "application locale"
        },
        "ui" : {
            "doseUnits": "ui",
            "route": "injectable"
        },
        "implant": {
            "doseUnits": "implant",
            "route": "injectable"
        },
        "Sachet": {
            "doseUnits": "Sachet",
            "route": "À manger"
        }
        }
      },
      "drugOrderHistoryConfig" :{
        "numberOfVisits" : 5
      }
    }
  }
}
